{
  "nodes": [
    {
      "id": "d_bsse_projects_cashly_shopping_expense_tracker_frontend_src_layouts_authlayout_tsx",
      "label": "AuthLayout.tsx",
      "file_type": "code",
      "source_file": "D:\\BSSE\\Projects\\CASHLY\\shopping-expense-tracker\\frontend\\src\\layouts\\AuthLayout.tsx",
      "source_location": "L1"
    }
  ],
  "edges": [
    {
      "source": "d_bsse_projects_cashly_shopping_expense_tracker_frontend_src_layouts_authlayout_tsx",
      "target": "react",
      "relation": "imports_from",
      "confidence": "EXTRACTED",
      "source_file": "D:\\BSSE\\Projects\\CASHLY\\shopping-expense-tracker\\frontend\\src\\layouts\\AuthLayout.tsx",
      "source_location": "L2",
      "weight": 1.0
    },
    {
      "source": "d_bsse_projects_cashly_shopping_expense_tracker_frontend_src_layouts_authlayout_tsx",
      "target": "react_router_dom",
      "relation": "imports_from",
      "confidence": "EXTRACTED",
      "source_file": "D:\\BSSE\\Projects\\CASHLY\\shopping-expense-tracker\\frontend\\src\\layouts\\AuthLayout.tsx",
      "source_location": "L3",
      "weight": 1.0
    },
    {
      "source": "d_bsse_projects_cashly_shopping_expense_tracker_frontend_src_layouts_authlayout_tsx",
      "target": "framer_motion",
      "relation": "imports_from",
      "confidence": "EXTRACTED",
      "source_file": "D:\\BSSE\\Projects\\CASHLY\\shopping-expense-tracker\\frontend\\src\\layouts\\AuthLayout.tsx",
      "source_location": "L4",
      "weight": 1.0
    },
    {
      "source": "d_bsse_projects_cashly_shopping_expense_tracker_frontend_src_layouts_authlayout_tsx",
      "target": "lucide_react",
      "relation": "imports_from",
      "confidence": "EXTRACTED",
      "source_file": "D:\\BSSE\\Projects\\CASHLY\\shopping-expense-tracker\\frontend\\src\\layouts\\AuthLayout.tsx",
      "source_location": "L5",
      "weight": 1.0
    },
    {
      "source": "d_bsse_projects_cashly_shopping_expense_tracker_frontend_src_layouts_authlayout_tsx",
      "target": "d_bsse_projects_cashly_shopping_expense_tracker_frontend_src_config_branding",
      "relation": "imports_from",
      "confidence": "EXTRACTED",
      "source_file": "D:\\BSSE\\Projects\\CASHLY\\shopping-expense-tracker\\frontend\\src\\layouts\\AuthLayout.tsx",
      "source_location": "L6",
      "weight": 1.0
    }
  ],
  "raw_calls": []
}
