{
  "nodes": [
    {
      "id": "d_bsse_projects_cashly_shopping_expense_tracker_frontend_src_hooks_useextensionsync_ts",
      "label": "useExtensionSync.ts",
      "file_type": "code",
      "source_file": "D:\\BSSE\\Projects\\CASHLY\\shopping-expense-tracker\\frontend\\src\\hooks\\useExtensionSync.ts",
      "source_location": "L1"
    },
    {
      "id": "hooks_useextensionsync_broadcastsyncstatus",
      "label": "broadcastSyncStatus()",
      "file_type": "code",
      "source_file": "D:\\BSSE\\Projects\\CASHLY\\shopping-expense-tracker\\frontend\\src\\hooks\\useExtensionSync.ts",
      "source_location": "L34"
    },
    {
      "id": "hooks_useextensionsync_useextensionsync",
      "label": "useExtensionSync()",
      "file_type": "code",
      "source_file": "D:\\BSSE\\Projects\\CASHLY\\shopping-expense-tracker\\frontend\\src\\hooks\\useExtensionSync.ts",
      "source_location": "L67"
    }
  ],
  "edges": [
    {
      "source": "d_bsse_projects_cashly_shopping_expense_tracker_frontend_src_hooks_useextensionsync_ts",
      "target": "react",
      "relation": "imports_from",
      "confidence": "EXTRACTED",
      "source_file": "D:\\BSSE\\Projects\\CASHLY\\shopping-expense-tracker\\frontend\\src\\hooks\\useExtensionSync.ts",
      "source_location": "L3",
      "weight": 1.0
    },
    {
      "source": "d_bsse_projects_cashly_shopping_expense_tracker_frontend_src_hooks_useextensionsync_ts",
      "target": "sonner",
      "relation": "imports_from",
      "confidence": "EXTRACTED",
      "source_file": "D:\\BSSE\\Projects\\CASHLY\\shopping-expense-tracker\\frontend\\src\\hooks\\useExtensionSync.ts",
      "source_location": "L4",
      "weight": 1.0
    },
    {
      "source": "d_bsse_projects_cashly_shopping_expense_tracker_frontend_src_hooks_useextensionsync_ts",
      "target": "d_bsse_projects_cashly_shopping_expense_tracker_frontend_src_services_genztoast",
      "relation": "imports_from",
      "confidence": "EXTRACTED",
      "source_file": "D:\\BSSE\\Projects\\CASHLY\\shopping-expense-tracker\\frontend\\src\\hooks\\useExtensionSync.ts",
      "source_location": "L5",
      "weight": 1.0
    },
    {
      "source": "d_bsse_projects_cashly_shopping_expense_tracker_frontend_src_hooks_useextensionsync_ts",
      "target": "d_bsse_projects_cashly_shopping_expense_tracker_frontend_src_config_supabase",
      "relation": "imports_from",
      "confidence": "EXTRACTED",
      "source_file": "D:\\BSSE\\Projects\\CASHLY\\shopping-expense-tracker\\frontend\\src\\hooks\\useExtensionSync.ts",
      "source_location": "L6",
      "weight": 1.0
    },
    {
      "source": "d_bsse_projects_cashly_shopping_expense_tracker_frontend_src_hooks_useextensionsync_ts",
      "target": "d_bsse_projects_cashly_shopping_expense_tracker_frontend_src_store_usestore",
      "relation": "imports_from",
      "confidence": "EXTRACTED",
      "source_file": "D:\\BSSE\\Projects\\CASHLY\\shopping-expense-tracker\\frontend\\src\\hooks\\useExtensionSync.ts",
      "source_location": "L7",
      "weight": 1.0
    },
    {
      "source": "d_bsse_projects_cashly_shopping_expense_tracker_frontend_src_hooks_useextensionsync_ts",
      "target": "hooks_useextensionsync_broadcastsyncstatus",
      "relation": "contains",
      "confidence": "EXTRACTED",
      "source_file": "D:\\BSSE\\Projects\\CASHLY\\shopping-expense-tracker\\frontend\\src\\hooks\\useExtensionSync.ts",
      "source_location": "L34",
      "weight": 1.0
    },
    {
      "source": "d_bsse_projects_cashly_shopping_expense_tracker_frontend_src_hooks_useextensionsync_ts",
      "target": "hooks_useextensionsync_useextensionsync",
      "relation": "contains",
      "confidence": "EXTRACTED",
      "source_file": "D:\\BSSE\\Projects\\CASHLY\\shopping-expense-tracker\\frontend\\src\\hooks\\useExtensionSync.ts",
      "source_location": "L67",
      "weight": 1.0
    }
  ],
  "raw_calls": [
    {
      "caller_nid": "hooks_useextensionsync_broadcastsyncstatus",
      "callee": "getSession",
      "is_member_call": true,
      "source_file": "D:\\BSSE\\Projects\\CASHLY\\shopping-expense-tracker\\frontend\\src\\hooks\\useExtensionSync.ts",
      "source_location": "L37"
    },
    {
      "caller_nid": "hooks_useextensionsync_broadcastsyncstatus",
      "callee": "warn",
      "is_member_call": true,
      "source_file": "D:\\BSSE\\Projects\\CASHLY\\shopping-expense-tracker\\frontend\\src\\hooks\\useExtensionSync.ts",
      "source_location": "L39"
    },
    {
      "caller_nid": "hooks_useextensionsync_broadcastsyncstatus",
      "callee": "channel",
      "is_member_call": true,
      "source_file": "D:\\BSSE\\Projects\\CASHLY\\shopping-expense-tracker\\frontend\\src\\hooks\\useExtensionSync.ts",
      "source_location": "L44"
    },
    {
      "caller_nid": "hooks_useextensionsync_broadcastsyncstatus",
      "callee": "subscribe",
      "is_member_call": true,
      "source_file": "D:\\BSSE\\Projects\\CASHLY\\shopping-expense-tracker\\frontend\\src\\hooks\\useExtensionSync.ts",
      "source_location": "L49"
    },
    {
      "caller_nid": "hooks_useextensionsync_useextensionsync",
      "callee": "useAuthStore",
      "is_member_call": false,
      "source_file": "D:\\BSSE\\Projects\\CASHLY\\shopping-expense-tracker\\frontend\\src\\hooks\\useExtensionSync.ts",
      "source_location": "L68"
    },
    {
      "caller_nid": "hooks_useextensionsync_useextensionsync",
      "callee": "useState",
      "is_member_call": false,
      "source_file": "D:\\BSSE\\Projects\\CASHLY\\shopping-expense-tracker\\frontend\\src\\hooks\\useExtensionSync.ts",
      "source_location": "L106"
    },
    {
      "caller_nid": "hooks_useextensionsync_useextensionsync",
      "callee": "useState",
      "is_member_call": false,
      "source_file": "D:\\BSSE\\Projects\\CASHLY\\shopping-expense-tracker\\frontend\\src\\hooks\\useExtensionSync.ts",
      "source_location": "L107"
    },
    {
      "caller_nid": "hooks_useextensionsync_useextensionsync",
      "callee": "useState",
      "is_member_call": false,
      "source_file": "D:\\BSSE\\Projects\\CASHLY\\shopping-expense-tracker\\frontend\\src\\hooks\\useExtensionSync.ts",
      "source_location": "L109"
    },
    {
      "caller_nid": "hooks_useextensionsync_useextensionsync",
      "callee": "useState",
      "is_member_call": false,
      "source_file": "D:\\BSSE\\Projects\\CASHLY\\shopping-expense-tracker\\frontend\\src\\hooks\\useExtensionSync.ts",
      "source_location": "L110"
    },
    {
      "caller_nid": "hooks_useextensionsync_useextensionsync",
      "callee": "useRef",
      "is_member_call": false,
      "source_file": "D:\\BSSE\\Projects\\CASHLY\\shopping-expense-tracker\\frontend\\src\\hooks\\useExtensionSync.ts",
      "source_location": "L113"
    },
    {
      "caller_nid": "hooks_useextensionsync_useextensionsync",
      "callee": "getCachedStatus",
      "is_member_call": false,
      "source_file": "D:\\BSSE\\Projects\\CASHLY\\shopping-expense-tracker\\frontend\\src\\hooks\\useExtensionSync.ts",
      "source_location": "L114"
    },
    {
      "caller_nid": "hooks_useextensionsync_useextensionsync",
      "callee": "useCallback",
      "is_member_call": false,
      "source_file": "D:\\BSSE\\Projects\\CASHLY\\shopping-expense-tracker\\frontend\\src\\hooks\\useExtensionSync.ts",
      "source_location": "L122"
    },
    {
      "caller_nid": "hooks_useextensionsync_useextensionsync",
      "callee": "useCallback",
      "is_member_call": false,
      "source_file": "D:\\BSSE\\Projects\\CASHLY\\shopping-expense-tracker\\frontend\\src\\hooks\\useExtensionSync.ts",
      "source_location": "L280"
    },
    {
      "caller_nid": "hooks_useextensionsync_useextensionsync",
      "callee": "useEffect",
      "is_member_call": false,
      "source_file": "D:\\BSSE\\Projects\\CASHLY\\shopping-expense-tracker\\frontend\\src\\hooks\\useExtensionSync.ts",
      "source_location": "L330"
    }
  ]
}
